src/__init__.py
src/config.py
src/config_file.py
src/errors.py
src/kokoro_cli.py
src/model_downloader.py
src/py.typed
src/tts_cli.py
src/utils.py
src/voice_cache.py
src/providers/__init__.py
src/providers/base.py
src/providers/elevenlabs.py
src/providers/kokoro_onnx.py
src/providers/openai.py
par_cli_tts-0.2.0.dist-info/METADATA
par_cli_tts-0.2.0.dist-info/WHEEL
par_cli_tts-0.2.0.dist-info/entry_points.txt
par_cli_tts-0.2.0.dist-info/licenses/LICENSE
par_cli_tts-0.2.0.dist-info/RECORD
