Metadata-Version: 2.4
Name: par-cli-tts
Version: 0.2.0
Summary: PAR CLI TTS - Command line text-to-speech tool using ElevenLabs with voice caching and name resolution
Project-URL: Homepage, https://github.com/paulrobello/par-cli-tts
Project-URL: Documentation, https://github.com/paulrobello/par-cli-tts/blob/main/README.md
Project-URL: Repository, https://github.com/paulrobello/par-cli-tts
Project-URL: Issues, https://github.com/paulrobello/par-cli-tts/issues
Project-URL: Discussions, https://github.com/paulrobello/par-cli-tts/discussions
Project-URL: Wiki, https://github.com/paulrobello/par-cli-tts/wiki
Author-email: Paul Robello <probello@gmail.com>
Maintainer-email: Paul Robello <probello@gmail.com>
License: MIT License
License-File: LICENSE
Keywords: audio,cli,elevenlabs,text-to-speech,tts
Classifier: Development Status :: 4 - Beta
Classifier: Environment :: Console
Classifier: Intended Audience :: Developers
Classifier: Intended Audience :: End Users/Desktop
Classifier: License :: OSI Approved :: MIT License
Classifier: Operating System :: MacOS
Classifier: Operating System :: Microsoft :: Windows :: Windows 10
Classifier: Operating System :: Microsoft :: Windows :: Windows 11
Classifier: Operating System :: POSIX :: Linux
Classifier: Programming Language :: Python :: 3
Classifier: Programming Language :: Python :: 3.11
Classifier: Programming Language :: Python :: 3.12
Classifier: Programming Language :: Python :: 3.13
Classifier: Topic :: Multimedia :: Sound/Audio :: Speech
Classifier: Topic :: Software Development :: Libraries :: Python Modules
Classifier: Typing :: Typed
Requires-Python: >=3.11
Requires-Dist: elevenlabs>=1.0.0
Requires-Dist: kokoro-onnx>=0.4.9
Requires-Dist: openai>=1.100.1
Requires-Dist: platformdirs>=4.3.0
Requires-Dist: python-dotenv>=1.0.0
Requires-Dist: pyyaml>=6.0.0
Requires-Dist: rich>=13.0.0
Requires-Dist: soundfile>=0.13.1
Requires-Dist: typer>=0.12.0
